{
    "version": "https://jsonfeed.org/version/1",
    "title": "Goyder Furniture",
    "description": "",
    "home_page_url": "https://aggoyder.github.io/gf-pages",
    "feed_url": "https://aggoyder.github.io/gf-pages/feed.json",
    "user_comment": "",
    "author": {
        "name": "Andrew"
    },
    "items": [
        {
            "id": "https://aggoyder.github.io/gf-pages/test-page.html",
            "url": "https://aggoyder.github.io/gf-pages/test-page.html",
            "title": "TEST PAGE",
            "summary": "Test first page",
            "content_html": "<p>Test first page</p>",
            "author": {
                "name": "Andrew"
            },
            "tags": [
            ],
            "date_published": "2026-03-20T16:38:17+00:00",
            "date_modified": "2026-03-20T16:38:17+00:00"
        }
    ]
}
